mbe_tools/__init__.py
mbe_tools/analysis.py
mbe_tools/cli.py
mbe_tools/cluster.py
mbe_tools/config.py
mbe_tools/hpc_templates.py
mbe_tools/input_builder.py
mbe_tools/jsonl_selector.py
mbe_tools/mbe.py
mbe_tools/mbe_math.py
mbe_tools/utils.py
mbe_tools/backends/base.py
mbe_tools/backends/orca.py
mbe_tools/backends/qchem.py
mbe_tools/parsers/base.py
mbe_tools/parsers/io.py
mbe_tools/parsers/orca.py
mbe_tools/parsers/qchem.py
mbe_tools-0.2.2.dist-info/METADATA
mbe_tools-0.2.2.dist-info/WHEEL
mbe_tools-0.2.2.dist-info/entry_points.txt
mbe_tools-0.2.2.dist-info/licenses/LICENSE
mbe_tools-0.2.2.dist-info/RECORD
