Metadata-Version: 2.4
Name: mbe-tools
Version: 0.2.2
Summary: A practical toolkit for Many-Body Expansion (MBE) workflows: cluster design, MBE input generation, output parsing, and analysis.
Author: Jiarui Wang
License: MIT
License-File: LICENSE
Requires-Python: >=3.10
Requires-Dist: numpy>=1.24
Requires-Dist: rich>=13.7
Requires-Dist: typer>=0.12
Provides-Extra: analysis
Requires-Dist: matplotlib>=3.8; extra == 'analysis'
Requires-Dist: openpyxl>=3.1; extra == 'analysis'
Requires-Dist: pandas>=2.0; extra == 'analysis'
Provides-Extra: cli
